kivy_file_manager_package/__init__.py
kivy_file_manager_package/file_manager.kv
kivy_file_manager_package/main.py
kivy_file_manager_package-2.0.dist-info/LICENSE
kivy_file_manager_package-2.0.dist-info/METADATA
kivy_file_manager_package-2.0.dist-info/WHEEL
kivy_file_manager_package-2.0.dist-info/entry_points.txt
kivy_file_manager_package-2.0.dist-info/top_level.txt
kivy_file_manager_package-2.0.dist-info/RECORD
