Metadata-Version: 2.1
Name: kivy-file-manager-package
Version: 2.0
Summary: Useful file manager app written in Kivy
Home-page: UNKNOWN
License: UNKNOWN
Platform: UNKNOWN
Requires-Python: >=3.6
License-File: LICENSE
Requires-Dist: kivy
